{"all": [{"temperature": 297.18, "icon": "04d", "time": 1588943916, "description": "overcast clouds", "clouds": 100}, {"temperature": 296.8, "icon": "04d", "time": 1588946400, "description": "overcast clouds", "clouds": 100}, {"temperature": 296.38, "icon": "04d", "time": 1588950000, "description": "overcast clouds", "clouds": 100}, {"temperature": 296.2, "icon": "04d", "time": 1588953600, "description": "overcast clouds", "clouds": 100}, {"temperature": 295.63, "icon": "04d", "time": 1588957200, "description": "overcast clouds", "clouds": 100}, {"temperature": 294.68, "icon": "04d", "time": 1588960800, "description": "overcast clouds", "clouds": 100}, {"temperature": 293.19, "icon": "04d", "time": 1588964400, "description": "broken clouds", "clouds": 65}, {"temperature": 292.13, "icon": "04n", "time": 1588968000, "description": "broken clouds", "clouds": 82}, {"temperature": 291.44, "icon": "04n", "time": 1588971600, "description": "overcast clouds", "clouds": 88}, {"temperature": 290.83, "icon": "04n", "time": 1588975200, "description": "overcast clouds", "clouds": 91}, {"temperature": 290.27, "icon": "04n", "time": 1588978800, "description": "overcast clouds", "clouds": 91}, {"temperature": 290.27, "icon": "04n", "time": 1588982400, "description": "overcast clouds", "clouds": 93}, {"temperature": 289.92, "icon": "04n", "time": 1588986000, "description": "overcast clouds", "clouds": 100}, {"temperature": 289.66, "icon": "04n", "time": 1588989600, "description": "overcast clouds", "clouds": 100}, {"temperature": 289.57, "icon": "04n", "time": 1588993200, "description": "overcast clouds", "clouds": 100}, {"temperature": 289.31, "icon": "04n", "time": 1588996800, "description": "overcast clouds", "clouds": 100}, {"temperature": 289.2, "icon": "04d", "time": 1589000400, "description": "overcast clouds", "clouds": 98}, {"temperature": 289.37, "icon": "04d", "time": 1589004000, "description": "overcast clouds", "clouds": 96}, {"temperature": 289.59, "icon": "04d", "time": 1589007600, "description": "overcast clouds", "clouds": 100}, {"temperature": 290.3, "icon": "04d", "time": 1589011200, "description": "overcast clouds", "clouds": 99}, {"temperature": 292.47, "icon": "04d", "time": 1589014800, "description": "overcast clouds", "clouds": 98}, {"temperature": 294.61, "icon": "04d", "time": 1589018400, "description": "overcast clouds", "clouds": 96}, {"temperature": 295.86, "icon": "10d", "time": 1589022000, "description": "light rain", "clouds": 97}, {"temperature": 296.68, "icon": "10d", "time": 1589025600, "description": "light rain", "clouds": 98}, {"temperature": 297.25, "icon": "10d", "time": 1589029200, "description": "light rain", "clouds": 98}, {"temperature": 295.53, "icon": "10d", "time": 1589032800, "description": "moderate rain", "clouds": 99}, {"temperature": 293.73, "icon": "10d", "time": 1589036400, "description": "moderate rain", "clouds": 100}, {"temperature": 293.22, "icon": "10d", "time": 1589040000, "description": "moderate rain", "clouds": 100}, {"temperature": 292.62, "icon": "10d", "time": 1589043600, "description": "light rain", "clouds": 100}, {"temperature": 292.26, "icon": "04d", "time": 1589047200, "description": "overcast clouds", "clouds": 100}, {"temperature": 291.57, "icon": "04d", "time": 1589050800, "description": "overcast clouds", "clouds": 100}, {"temperature": 291.02, "icon": "04n", "time": 1589054400, "description": "overcast clouds", "clouds": 100}, {"temperature": 290.34, "icon": "04n", "time": 1589058000, "description": "broken clouds", "clouds": 80}, {"temperature": 289.86, "icon": "04n", "time": 1589061600, "description": "broken clouds", "clouds": 65}, {"temperature": 289.46, "icon": "04n", "time": 1589065200, "description": "broken clouds", "clouds": 53}, {"temperature": 289.15, "icon": "04n", "time": 1589068800, "description": "broken clouds", "clouds": 52}, {"temperature": 288.94, "icon": "04n", "time": 1589072400, "description": "overcast clouds", "clouds": 100}, {"temperature": 288.66, "icon": "04n", "time": 1589076000, "description": "overcast clouds", "clouds": 100}, {"temperature": 288.48, "icon": "04n", "time": 1589079600, "description": "overcast clouds", "clouds": 100}, {"temperature": 288.47, "icon": "10n", "time": 1589083200, "description": "light rain", "clouds": 100}, {"temperature": 288.86, "icon": "10d", "time": 1589086800, "description": "light rain", "clouds": 100}, {"temperature": 289.37, "icon": "10d", "time": 1589090400, "description": "light rain", "clouds": 100}, {"temperature": 289.83, "icon": "10d", "time": 1589094000, "description": "light rain", "clouds": 100}, {"temperature": 289.63, "icon": "10d", "time": 1589097600, "description": "light rain", "clouds": 100}, {"temperature": 290.32, "icon": "04d", "time": 1589101200, "description": "overcast clouds", "clouds": 100}, {"temperature": 290.24, "icon": "10d", "time": 1589104800, "description": "light rain", "clouds": 100}, {"temperature": 290.58, "icon": "10d", "time": 1589108400, "description": "light rain", "clouds": 100}, {"temperature": 293.43, "icon": "10d", "time": 1589112000, "description": "light rain", "clouds": 100}], "time_fetched": 1588943917.0, "datetimes": [1588943916, 1588946400, 1588950000, 1588953600, 1588957200, 1588960800, 1588964400, 1588968000, 1588971600, 1588975200, 1588978800, 1588982400, 1588986000, 1588989600, 1588993200, 1588996800, 1589000400, 1589004000, 1589007600, 1589011200, 1589014800, 1589018400, 1589022000, 1589025600, 1589029200, 1589032800, 1589036400, 1589040000, 1589043600, 1589047200, 1589050800, 1589054400, 1589058000, 1589061600, 1589065200, 1589068800, 1589072400, 1589076000, 1589079600, 1589083200, 1589086800, 1589090400, 1589094000, 1589097600, 1589101200, 1589104800, 1589108400, 1589112000]}